{
  "lastUpdate": "2026-02-25T21:58:41.545Z",
  "products": [
    {
      "id": "item_1772056603249_oiluf",
      "display_title": "נעלי ספורט M SKYWARD X / גברים",
      "price_ils": 1100,
      "size_available": "Available",
      "sizes": [
        "41",
        "42",
        "42.5",
        "43",
        "44",
        "44.5",
        "45",
        "46",
        "46.5",
        "47",
        "48"
      ],
      "image_url": "https://media.terminalx.com/pub/media/catalog/product/cache/f112238e8de94b6d480bd02e7a9501b8/r/2/r283550010-11754302118.jpg?image_type_mobile=webp_jpeg_like_70",
      "badges": [],
      "buy_link": "https://www.terminalx.com/default-category/r283550010?color=5",
      "store_name": "TerminalX"
    },
    {
      "id": "item_1772056604244_hskt1",
      "display_title": "נעלי ספורט W SKYWARD X / נשים",
      "price_ils": 1100,
      "size_available": "Available",
      "sizes": [
        "37",
        "38",
        "38.5",
        "39",
        "40",
        "40.5",
        "42"
      ],
      "image_url": "https://media.terminalx.com/pub/media/catalog/product/cache/f112238e8de94b6d480bd02e7a9501b8/r/2/r283560010-11756388547.jpg?image_type_mobile=webp_jpeg_like_70",
      "badges": [],
      "buy_link": "https://www.terminalx.com/default-category/r283560010?color=5",
      "store_name": "TerminalX"
    },
    {
      "id": "item_1772056717589_71kr1",
      "display_title": "HOKA SKYWARD X - נעלי לגברים סקייווארד...",
      "price_ils": 1099.90934,
      "size_available": "Available",
      "sizes": [],
      "image_url": "https://sfycdn.speedsize.com/1f99ce09-afb7-4435-9b06-8c28d6b78b8e/https://weshoes.co.il/cdn/shop/files/HOK211M-FLP-1.jpg?v=1745331360&width=533",
      "badges": [],
      "buy_link": "https://www.weshoes.co.il/products/hok211m-flp?_pos=1&_sid=61c732247&_ss=r",
      "store_name": "WeShoes"
    },
    {
      "id": "item_1772056718553_rx2tb",
      "display_title": "HOKA SKYWARD X - נעלי לנשים סקייווארד...",
      "price_ils": 1099.90934,
      "size_available": "Available",
      "sizes": [],
      "image_url": "https://sfycdn.speedsize.com/1f99ce09-afb7-4435-9b06-8c28d6b78b8e/https://weshoes.co.il/cdn/shop/files/HOK211W-FLP-1.jpg?v=1765451728&width=533",
      "badges": [],
      "buy_link": "https://www.weshoes.co.il/products/hok211w-flp?_pos=2&_sid=61c732247&_ss=r",
      "store_name": "WeShoes"
    }
  ],
  "isScanning": false,
  "scheduledSearchEnabled": true
}